fastface/__init__.py
fastface/module.py
fastface/registry.yaml
fastface/version.py
fastface/adapter/__init__.py
fastface/adapter/extract_handler.py
fastface/adapter/gdrive.py
fastface/adapter/http.py
fastface/api/__init__.py
fastface/arch/__init__.py
fastface/arch/lffd/__init__.py
fastface/arch/lffd/module.py
fastface/arch/lffd/blocks/__init__.py
fastface/arch/lffd/blocks/anchor.py
fastface/arch/lffd/blocks/backbone_v1.py
fastface/arch/lffd/blocks/backbone_v2.py
fastface/arch/lffd/blocks/conv.py
fastface/arch/lffd/blocks/head.py
fastface/arch/lffd/blocks/resblock.py
fastface/dataset/__init__.py
fastface/dataset/base.py
fastface/dataset/fddb.py
fastface/dataset/widerface.py
fastface/loss/__init__.py
fastface/loss/focal_loss.py
fastface/loss/iou_loss.py
fastface/metric/__init__.py
fastface/metric/ap.py
fastface/metric/ar.py
fastface/metric/utils.py
fastface/metric/widerface_ap.py
fastface/metric/functional/__init__.py
fastface/metric/functional/ap.py
fastface/transforms/__init__.py
fastface/transforms/compose.py
fastface/transforms/discard.py
fastface/transforms/interpolate.py
fastface/transforms/normalize.py
fastface/transforms/pad.py
fastface/transforms/rotate.py
fastface/transforms/augmentation/__init__.py
fastface/transforms/augmentation/blur.py
fastface/transforms/augmentation/color_jitter.py
fastface/transforms/augmentation/lffd_random_sample.py
fastface/transforms/augmentation/random_horizontal_flip.py
fastface/transforms/augmentation/random_rotate.py
fastface/transforms/functional/__init__.py
fastface/transforms/functional/color_jitter.py
fastface/transforms/functional/interpolate.py
fastface/transforms/functional/pad.py
fastface/transforms/functional/rotate.py
fastface/utils/__init__.py
fastface/utils/box.py
fastface/utils/cache.py
fastface/utils/cluster.py
fastface/utils/config.py
fastface/utils/data.py
fastface/utils/geo.py
fastface/utils/kernel.py
fastface/utils/preprocess.py
fastface/utils/random.py
fastface/utils/vis.py
tests/__init__.py
fastface-0.1.4.dist-info/LICENSE
fastface-0.1.4.dist-info/METADATA
fastface-0.1.4.dist-info/WHEEL
fastface-0.1.4.dist-info/top_level.txt
fastface-0.1.4.dist-info/RECORD
