Metadata-Version: 2.1
Name: fastface
Version: 0.1.4
Summary: A face detection framework for edge devices using pytorch lightning
Home-page: https://github.com/borhanMorphy/light-face-detection
Author: Ömer BORHAN
Author-email: borhano.f.42@gmail.com
License: MIT
Project-URL: Documentation, https://fastface.readthedocs.io/en/latest/
Keywords: pytorch_lightning,face detection,edge AI,LFFD
Classifier: Environment :: Console
Classifier: Natural Language :: English
Classifier: Intended Audience :: Developers
Classifier: Intended Audience :: Science/Research
Classifier: Topic :: Scientific/Engineering :: Artificial Intelligence
Classifier: Programming Language :: Python :: 3
Classifier: Programming Language :: Python :: 3.8
License-File: LICENSE
Requires-Dist: pytorch-lightning (==1.8.*)
Requires-Dist: torch (>=1.8.1)
Requires-Dist: torchvision (>=0.9.0)
Requires-Dist: torchmetrics (==1.*)
Requires-Dist: imageio (~=2.9.0)
Requires-Dist: scipy (==1.10.1)
Requires-Dist: googledrivedownloader (==0.4)
Requires-Dist: requests (~=2.25.0)
Requires-Dist: PyYAML (~=5.4.1)
Requires-Dist: checksumdir (==1.2.*)
Provides-Extra: all
Requires-Dist: isort ; extra == 'all'
Requires-Dist: black ; extra == 'all'
Requires-Dist: flake8 ; extra == 'all'
Requires-Dist: tox ; extra == 'all'
Requires-Dist: tox-conda ; extra == 'all'
Requires-Dist: pytest ; extra == 'all'
Requires-Dist: pytest-pylint ; extra == 'all'
Requires-Dist: pytest-cov ; extra == 'all'
Requires-Dist: sphinxemoji ; extra == 'all'
Requires-Dist: sphinx-rtd-theme ; extra == 'all'
Requires-Dist: recommonmark ; extra == 'all'
Requires-Dist: sphinx-markdown-tables ; extra == 'all'
Requires-Dist: sphinxcontrib-napoleon ; extra == 'all'
Provides-Extra: dev
Requires-Dist: isort ; extra == 'dev'
Requires-Dist: black ; extra == 'dev'
Requires-Dist: flake8 ; extra == 'dev'
Requires-Dist: tox ; extra == 'dev'
Requires-Dist: tox-conda ; extra == 'dev'
Requires-Dist: pytest ; extra == 'dev'
Requires-Dist: pytest-pylint ; extra == 'dev'
Requires-Dist: pytest-cov ; extra == 'dev'
Requires-Dist: sphinxemoji ; extra == 'dev'
Requires-Dist: sphinx-rtd-theme ; extra == 'dev'
Requires-Dist: recommonmark ; extra == 'dev'
Requires-Dist: sphinx-markdown-tables ; extra == 'dev'
Requires-Dist: sphinxcontrib-napoleon ; extra == 'dev'
Provides-Extra: docs
Requires-Dist: sphinxemoji ; extra == 'docs'
Requires-Dist: sphinx-rtd-theme ; extra == 'docs'
Requires-Dist: recommonmark ; extra == 'docs'
Requires-Dist: sphinx-markdown-tables ; extra == 'docs'
Requires-Dist: sphinxcontrib-napoleon ; extra == 'docs'
Provides-Extra: test
Requires-Dist: pytest ; extra == 'test'
Requires-Dist: pytest-pylint ; extra == 'test'
Requires-Dist: pytest-cov ; extra == 'test'
